nsd_utils/__init__.py
nsd_utils/collect_project_code.py
nsd_utils/admin/__init__.py
nsd_utils/admin_panel/__init__.py
nsd_utils/admin_panel/admin_handlers.py
nsd_utils/aiogram_utils/__init__.py
nsd_utils/aiogram_utils/callback_data.py
nsd_utils/aiogram_utils/file_manager.py
nsd_utils/aiogram_utils/safe_send.py
nsd_utils/aiogram_utils/text_templates.py
nsd_utils/cache/__init__.py
nsd_utils/cache/cache_core.py
nsd_utils/cache/cache_decorator.py
nsd_utils/db/__init__.py
nsd_utils/db/crud.py
nsd_utils/db/migration_manager.py
nsd_utils/db/models.py
nsd_utils/db/session_manager.py
nsd_utils/filters/__init__.py
nsd_utils/filters/chat_type.py
nsd_utils/fsm/__init__.py
nsd_utils/fsm/extended_wizard.py
nsd_utils/fsm/wizard.py
nsd_utils/i18n/__init__.py
nsd_utils/i18n/l10n.py
nsd_utils/inline_menus/__init__.py
nsd_utils/inline_menus/menu_builder.py
nsd_utils/inline_menus/paginator.py
nsd_utils/logging/__init__.py
nsd_utils/logging/log_helpers.py
nsd_utils/logging/logger_core.py
nsd_utils/notifications/__init__.py
nsd_utils/notifications/event_bus.py
nsd_utils/scheduler/__init__.py
nsd_utils/scheduler/tasks.py
nsd_utils/security/__init__.py
nsd_utils/security/log_all.py
nsd_utils/security/menu_ownership.py
nsd_utils/security/rate_limit.py
nsd_utils/security/rbac.py
nsd_utils/utils/__init__.py
nsd_utils/utils/handlers_loader.py
nsd_utils/utils/users.py
nsd_utils-0.2.0.dist-info/METADATA
nsd_utils-0.2.0.dist-info/WHEEL
nsd_utils-0.2.0.dist-info/top_level.txt
nsd_utils-0.2.0.dist-info/RECORD
